nbmediasplit/__init__.py
nbmediasplit/nbmediasplit.py
nbmediasplit-0.2.0.dist-info/entry_points.txt
nbmediasplit-0.2.0.dist-info/WHEEL
nbmediasplit-0.2.0.dist-info/METADATA
nbmediasplit-0.2.0.dist-info/RECORD
