Metadata-Version: 2.1
Name: nbmediasplit
Version: 0.2.0
Summary: 
Home-page: https://github.com/wrist/nbmediasplit
License: MIT
Author: wrist
Author-email: stoicheia1986@gmail.com
Requires-Python: >=3.5,<4.0
Classifier: License :: OSI Approved :: MIT License
Classifier: Programming Language :: Python :: 3
Classifier: Programming Language :: Python :: 3.5
Classifier: Programming Language :: Python :: 3.6
Classifier: Programming Language :: Python :: 3.7
Requires-Dist: beautifulsoup4 (>=4.9,<5.0)
Requires-Dist: click (>=7.1,<8.0)
Requires-Dist: lxml (>=4.5,<5.0)
Project-URL: Repository, https://github.com/wrist/nbmediasplit
